{
    "Account": "",
    "Counterparty": "",
    "Code": "",
    "ID": "",
    "ENTITY": "",
    "DESCRIPTION": "",
    "VALUEDATE": "",
    "AMOUNT": "",
    "TRANSACTION_METHOD": "",
    "DATE": "",
    "TRANSACTION_TYPE": "",
    "CATEGORY_TAGS": [],
    "TELT_MEE": true,
    "ENTITY_ALIAS": "",
    "NATUURLIJK_PERSOON": false,
    "VERANTWOORDING": "",
    "GESPLITSTE_TRANSACTIE": false,
    "ORIGINEEL_BERICHT": "",
    "RECURRING": false,
    "OPENSTAAND": false,
    "VERWERKT": "",
    "LOCALHOST_TRANSACTION": false
}